{
	"forge_marker": 1,
	"defaults": {
		"model": "cross"
	},
	"variants": {
		"age": {
			"0": {
				"textures": {
					"cross": "hellskitchen:blocks/hypnoflower/0"
				}
			},
			"1": {
				"textures": {
					"cross": "hellskitchen:blocks/hypnoflower/0"
				}
			},
			"2": {
				"textures": {
					"cross": "hellskitchen:blocks/hypnoflower/1"
				}
			},
			"3": {
				"textures": {
					"cross": "hellskitchen:blocks/hypnoflower/1"
				}
			},
			"4": {
				"textures": {
					"cross": "hellskitchen:blocks/hypnoflower/2"
				}
			},
			"5": {
				"textures": {
					"cross": "hellskitchen:blocks/hypnoflower/2"
				}
			},
			"6": {
				"textures": {
					"cross": "hellskitchen:blocks/hypnoflower/2"
				}
			},
			"7": {
				"textures": {
					"cross": "hellskitchen:blocks/hypnoflower/3"
				}
			}
		}
	}
}
